MANIFEST.in
README.md
setup.py
fir.egg-info/PKG-INFO
fir.egg-info/SOURCES.txt
fir.egg-info/dependency_links.txt
fir.egg-info/not-zip-safe
fir.egg-info/top_level.txt
src/FIRDeconvolution.py
src/__init__.py
src/test/FIRDeconvolution_test.ipynb
src/test/pupil_preprocess_python.ipynb
src/test/test.py
src/test/.ipynb_checkpoints/FIRDeconvolution_test-checkpoint.ipynb
src/test/.ipynb_checkpoints/pupil_preprocess_python-checkpoint.ipynb