Metadata-Version: 1.1
Name: fir
Version: 0.0.2
Summary: Finite Impulse Response package for time series analysis.
Home-page: http://tknapen.github.io/FIRDeconvolution
Author: Tomas Knapen
Author-email: tknapen@gmail.com
License: The MIT License (MIT)
Download-URL: https://github.com/tknapen/FIRDeconvolution
Platform: any
Classifier: Intended Audience :: Science/Research
Classifier: Intended Audience :: Developers
Classifier: License :: OSI Approved
Classifier: Programming Language :: Python
Classifier: Topic :: Software Development
Classifier: Topic :: Scientific/Engineering
Classifier: Operating System :: POSIX
Classifier: Operating System :: Unix
Classifier: Operating System :: MacOS
